setup.py
fabric_aws/__init__.py
fabric_aws.egg-info/PKG-INFO
fabric_aws.egg-info/SOURCES.txt
fabric_aws.egg-info/dependency_links.txt
fabric_aws.egg-info/requires.txt
fabric_aws.egg-info/top_level.txt