Metadata-Version: 1.1
Name: fabric-aws
Version: 0.1
Summary: Fabric integration with AWS Autoscaling Groups (+Cloudformation)
Home-page: http://github.com/EverythingMe/fabric-aws
Author: EverythingMe
Author-email: omrib@everything.me
License: UNKNOWN
Platform: UNKNOWN
Classifier: Development Status :: 5 - Production/Stable
Classifier: Environment :: Console
Classifier: Intended Audience :: Developers
Classifier: Intended Audience :: System Administrators
Classifier: Operating System :: OS Independent
Classifier: Programming Language :: Python :: 2.7
Classifier: Topic :: System :: Clustering
Classifier: Topic :: System :: Systems Administration
Classifier: Topic :: Utilities
